Metadata-Version: 2.1
Name: fc-bigdata1
Version: 2.0
Summary: 这个是一个只有两个变量的包
Home-page: UNKNOWN
Author: 大数据1
Author-email: fc@bigdata.com
License: UNKNOWN
Platform: UNKNOWN
